Verilog/Lab 2/gray_counter.v
`timescale 1ns/10ps
module gray_counter(out,clk,clr);

	input clk, clr;

	output [3:0] out;

	reg [3:0] tmp;

	always @(posedge clk)
	begin

		if (clr)
			tmp <= 4'b0000;
		else
			tmp <= tmp + 1'b1;

	end

	assign out[3] = tmp[3];
	assign out[2] = tmp[3] ^ tmp[2];
	assign out[1] = tmp[2] ^ tmp[1];
	assign out[0] = tmp[1] ^ tmp[0];

endmodule

Verilog/Lab 2/test_gray.v
`timescale 1ns/10ps
`include "gray_counter.v"
module test;


  reg clr = 0;
  initial begin
     $dumpfile("gray_test.vcd");
     $dumpvars(0,test);
     //$monitor("At time %t, count = %d",$time, out);

	clr = 0;
	# 1 clr = 1;
	# 2 clr = 0;

	# 50 clr = 1;
	# 51 clr = 0;

    # 513 $finish;
  end

  reg clk = 0;
  always #1 clk = !clk;

  wire [3:0] out;
  gray_counter c1 (out,clk,clr);

  initial
     $monitor("At time %t, value = %b (%0d)",$time, out, out);
endmodule // test

Verilog/Lab 2/gray_test.vcd
$date
	Mon Oct 14 11:41:27 2019
$end
$version
	Icarus Verilog
$end
$timescale
	10ps
$end
$scope module test $end
$var wire 4 ! out [3:0] $end
$var reg 1 " clk $end
$var reg 1 # clr $end
$scope module c1 $end
$var wire 1 " clk $end
$var wire 1 # clr $end
$var wire 4 $ out [3:0] $end
$var reg 4 % tmp [3:0] $end
$upscope $end
$upscope $end
$enddefinitions $end
#0
$dumpvars
bx %
bx $
0#
0"
bx !
$end
#100
b0 !
b0 $
b0 %
1"
1#
#200
0"
#300
b1 !
b1 $
b1 %
1"
0#
#400
0"
#500
b11 !
b11 $
b10 %
1"
#600
0"
#700
b10 !
b10 $
b11 %
1"
#800
0"
#900
b110 !
b110 $
b100 %
1"
#1000
0"
#1100
b111 !
b111 $
b101 %
1"
#1200
0"
#1300
b101 !
b101 $
b110 %
1"
#1400
0"
#1500
b100 !
b100 $
b111 %
1"
#1600
0"
#1700
b1100 !
b1100 $
b1000 %
1"
#1800
0"
#1900
b1101 !
b1101 $
b1001 %
1"
#2000
0"
#2100
b1111 !
b1111 $
b1010 %
1"
#2200
0"
#2300
b1110 !
b1110 $
b1011 %
1"
#2400
0"
#2500
b1010 !
b1010 $
b1100 %
1"
#2600
0"
#2700
b1011 !
b1011 $
b1101 %
1"
#2800
0"
#2900
b1001 !
b1001 $
b1110 %
1"
#3000
0"
#3100
b1000 !
b1000 $
b1111 %
1"
#3200
0"
#3300
b0 !
b0 $
b0 %
1"
#3400
0"
#3500
b1 !
b1 $
b1 %
1"
#3600
0"
#3700
b11 !
b11 $
b10 %
1"
#3800
0"
#3900
b10 !
b10 $
b11 %
1"
#4000
0"
#4100
b110 !
b110 $
b100 %
1"
#4200
0"
#4300
b111 !
b111 $
b101 %
1"
#4400
0"
#4500
b101 !
b101 $
b110 %
1"
#4600
0"
#4700
b100 !
b100 $
b111 %
1"
#4800
0"
#4900
b1100 !
b1100 $
b1000 %
1"
#5000
0"
#5100
b1101 !
b1101 $
b1001 %
1"
#5200
0"
#5300
b0 !
b0 $
b0 %
1"
1#
