Verilog/Lab 3/8_1_mux.v
module mux_8_1 (in, sel, out);
	
	input [7:0] in;
	input [2:0] sel;
	
	output out;
	
	assign out =( (~sel[2] & ~sel[1] & ~sel[0] & in[0]) 
				| (~sel[2] & ~sel[1] & sel[0] & in[1]) 
				| (~sel[2] & sel[1] & ~sel[0] & in[2]) 
				| (~sel[2] & sel[1] & sel[0] & in[3]) 
				| (sel[2] & ~sel[1] & ~sel[0] & in[4]) 
				| (sel[2] & ~sel[1] & sel[0] & in[5]) 
				| (sel[2] & sel[1] & ~sel[0] & in[6]) 
				| (sel[2] & sel[1] & sel[0] & in[7]));
	
endmodule

Verilog/Lab 3/8_1_mux_test.v
`timescale 1ns/10ps
module mux_8_1_test;
	
	wire out;
	reg [7:0]in = 8'b01010101;
	reg [2:0]sel;
	
	initial
	begin
		$dumpfile("mux_8_1_test.vcd");
		$dumpvars(0,mux_8_1_test);
		$monitor("sel %b out %b", sel, out);
		
		# 0 sel = 3'b000;
		
		# 5 sel = 3'b001;
		
		# 5 sel = 3'b010;
		
		# 5 sel = 3'b011;
		
		# 5 sel = 3'b100;
		
		# 5 sel = 3'b101;
		
		# 5 sel = 3'b110;
		
		# 5 sel = 3'b111;
		
		# 5 $finish;
		
	end
	
	mux_8_1 m1 (in, sel, out);
endmodule

Verilog/Lab 3/mux_8_1_test.vcd
$date
	Sun Nov 30 19:18:09 2014
$end
$version
	Icarus Verilog
$end
$timescale
	10ps
$end
$scope module mux_8_1_test $end
$var wire 1 ! out $end
$var reg 8 " in [7:0] $end
$var reg 3 # sel [2:0] $end
$scope module m1 $end
$var wire 8 $ in [7:0] $end
$var wire 1 ! out $end
$var wire 3 % sel [2:0] $end
$upscope $end
$upscope $end
$enddefinitions $end
#0
$dumpvars
b0 %
b1010101 $
b0 #
b1010101 "
1!
$end
#500
0!
b1 #
b1 %
#1000
1!
b10 #
b10 %
#1500
0!
b11 #
b11 %
#2000
1!
b100 #
b100 %
#2500
0!
b101 #
b101 %
#3000
1!
b110 #
b110 %
#3500
0!
b111 #
b111 %
