Verilog/Lab 4/sequence_analyse.v
module sequence_analyse( in, out, clk, rst);
	
	output reg out;
	input in, clk, rst;
	
	reg [1:0] c_state; 
	reg [1:0] n_state;
	
	parameter zero_0_1 = 2'b00, one_1 = 2'b10, one_0 = 2'b01; 
	
	always @ (in or c_state)
	begin
		
		n_state = c_state;
		out = 1'b0;
		
		case(c_state)
			
			zero_0_1: 
			begin
				if (in)
					begin
					n_state = one_1;
					out = 1'b0;
					end 
				else
					begin
					n_state = one_0;
					out = 1'b0;
					end 
			end
			
			one_1:
			begin
				if (in)
					begin
						n_state = one_1;
						out = 1'b1;
					end
				else
					begin
						n_state = one_0;
						out = 1'b0;
					end
			end
			
			one_0:
			begin
				if (in)
					begin
						n_state = one_1;
						out = 1'b0;
					end 
				else
					begin
						n_state = one_0;
						out = 1'b1;
					end
			end
			
			default:
			begin
				n_state = zero_0_1;
				out = 1'b0;
			end 
		endcase
	end
	
	always @ (posedge clk)
	begin
		if(rst)
			c_state <= zero_0_1;
		else
			c_state <= n_state;
	end  
	
endmodule

Verilog/Lab 4/sequence_analyse_test.v
`timescale 1ns/10ps
module sequence_analyse_test;
	
	reg clk = 0;  
	reg rst = 1;
	reg in = 0;
	
	wire out;
	
	always #1 clk = ~clk;
	
	initial 
	begin
		$dumpfile("sequence_analyse_test.vcd");
		$dumpvars(0, sequence_analyse_test);
		$monitor("in %b out %b", in, out);
		 
		
		# 5 rst <= 0;
		
		# 0 in <= 1;
		# 5 in <= 0;
		# 5 in <= 1;
		# 5 in <= 1;
		# 5 in <= 0;
		# 5 in <= 0;
		# 5 in <= 1; 
		# 0 in <= 0;
		
		# 5 in <= 1;
		# 5 in <= 0; 
		# 0 in <= 1;
		
		# 500 $finish; 
		
	end
	sequence_analyse s1 ( in, out, clk, rst);
endmodule

Verilog/Lab 4/sequence_analyse_test.vcd
$date
	Thu Dec 18 16:34:18 2014
$end
$version
	Icarus Verilog
$end
$timescale
	10ps
$end
$scope module sequence_analyse_test $end
$var wire 1 ! out $end
$var reg 1 " clk $end
$var reg 1 # in $end
$var reg 1 $ rst $end
$scope module s1 $end
$var wire 1 % clk $end
$var wire 1 & in $end
$var wire 1 ' rst $end
$var reg 2 ( c_state [1:0] $end
$var reg 2 ) n_state [1:0] $end
$var reg 1 * out $end
$upscope $end
$upscope $end
$enddefinitions $end
#0
$dumpvars
0*
b0 )
bx (
1'
0&
0%
1$
0#
0"
0!
$end
#100
b1 )
b0 (
1"
1%
#200
0"
0%
#300
1"
1%
#400
0"
0%
#500
b10 )
1#
1&
0$
0'
1"
1%
#600
0"
0%
#700
1*
1!
b10 (
1"
1%
#800
0"
0%
#900
1"
1%
#1000
b1 )
0*
0!
0#
0&
0"
0%
#1100
1*
1!
b1 (
1"
1%
#1200
0"
0%
#1300
1"
1%
#1400
0"
0%
#1500
b10 )
0*
0!
1#
1&
1"
1%
#1600
0"
0%
#1700
1*
1!
b10 (
1"
1%
#1800
0"
0%
#1900
1"
1%
#2000
0"
0%
#2100
1"
1%
#2200
0"
0%
#2300
1"
1%
#2400
0"
0%
#2500
b1 )
0*
0!
0#
0&
1"
1%
#2600
0"
0%
#2700
1*
1!
b1 (
1"
1%
#2800
0"
0%
#2900
1"
1%
#3000
0"
0%
#3100
1"
1%
#3200
0"
0%
#3300
1"
1%
#3400
0"
0%
#3500
1*
1!
0#
0&
1"
1%
#3600
0"
0%
#3700
1"
1%
#3800
0"
0%
#3900
1"
1%
#4000
b10 )
0*
0!
1#
1&
0"
0%
#4100
1*
1!
b10 (
1"
1%
#4200
0"
0%
#4300
1"
1%
#4400
0"
0%
#4500
1*
1!
1#
1&
1"
1%
