Verilog/Lab 4/venting_mealy.v
module venting_mealy (clk, reset, in5, in10, door);
	
	input clk, in5, in10, reset;
	
	output reg door;
	
	reg [1:0] state;
	reg [1:0] n_state;
	
	parameter zero_cents = 2'b00, five_cents = 2'b01, ten_cents = 2'b10, fifteen_cents = 2'b11; 
	
	always @ (in5 or in10 or state)
		
		case (state)
			zero_cents:
			begin
				if (in10)
				begin
					n_state = ten_cents;
					door = 0;
				end
				
				else if (in5)
				begin
					n_state = five_cents;
					door = 0;
				end
				
				else
				begin
					n_state = zero_cents;
					door = 0;
				end
			end
			
			five_cents:
			begin
				if (in5)
				begin
					n_state = ten_cents;
					door = 0;
				end
				
				else if (in10)
				begin
					n_state = fifteen_cents;
					door = 0;
				end
				
				else 
				begin
					n_state = five_cents;
					door = 0;
				end
			end
			
			ten_cents:
			begin
				if (in5)
				begin
					n_state = fifteen_cents;
					door = 0;
				end
				
				else if(in10)
				begin
					n_state = zero_cents;
					door = 1;
				end
				
				else
				begin
					n_state = ten_cents;
					door = 0;
				end
			end
			
			fifteen_cents:
			begin
				if (in5 || in10)
				begin
					n_state = zero_cents;
					door = 1;
				end
				
				else 
				begin
					n_state = fifteen_cents;
					door = 0;
				end
				
			end
		endcase
		
	always @ (posedge clk)
		if (reset)
			state <= zero_cents;
		else
			state <= n_state;
	
endmodule

Verilog/Lab 4/venting_mealy_test.v
`timescale 1ns/10ps
module venting_mealy_test;
	
	reg clk = 0;  
	reg reset = 1;
	reg in5 = 0;
	reg in10 = 0;
	
	wire door;
	
	always #1 clk = ~clk;
	
	initial 
	begin
		$dumpfile("venting_mealy_test.vcd");
		$dumpvars(0, venting_mealy_test);
		$monitor("in5 %b in10 %b door %b", in5, in10, door);
		
		# 5 reset <= 0;
		
		# 5 in10 <= 1;
		# 5 in10 <= 0;
		
		# 5 in5 <= 1;
		# 5 in5 <= 0;
		
		# 5 in5 <= 1;
		# 5 in5 <= 0;
		
		# 5 in10 <= 1;
		# 5 in10 <= 0;
		
		# 50 $finish; 
		
	end
	venting_mealy v1 (clk, reset, in5, in10, door);
endmodule

Verilog/Lab 4/venting_mealy_test.vcd
$date
	Thu Dec 18 17:04:54 2014
$end
$version
	Icarus Verilog
$end
$timescale
	10ps
$end
$scope module venting_mealy_test $end
$var wire 1 ! door $end
$var reg 1 " clk $end
$var reg 1 # in10 $end
$var reg 1 $ in5 $end
$var reg 1 % reset $end
$scope module v1 $end
$var wire 1 & clk $end
$var wire 1 ' in10 $end
$var wire 1 ( in5 $end
$var wire 1 ) reset $end
$var reg 1 * door $end
$var reg 2 + n_state [1:0] $end
$var reg 2 , state [1:0] $end
$upscope $end
$upscope $end
$enddefinitions $end
#0
$dumpvars
bx ,
bx +
x*
1)
0(
0'
0&
1%
0$
0#
0"
x!
$end
#100
0*
0!
b0 +
b0 ,
1"
1&
#200
0"
0&
#300
1"
1&
#400
0"
0&
#500
0%
0)
1"
1&
#600
0"
0&
#700
1"
1&
#800
0"
0&
#900
1"
1&
#1000
b10 +
1#
1'
0"
0&
#1100
1*
1!
b0 +
b10 ,
1"
1&
#1200
0"
0&
#1300
0*
0!
b10 +
b0 ,
1"
1&
#1400
0"
0&
#1500
b10 ,
0#
0'
1"
1&
#1600
0"
0&
#1700
1"
1&
#1800
0"
0&
#1900
1"
1&
#2000
b11 +
1$
1(
0"
0&
#2100
1*
1!
b0 +
b11 ,
1"
1&
#2200
0"
0&
#2300
0*
0!
b1 +
b0 ,
1"
1&
#2400
0"
0&
#2500
b1 ,
0$
0(
1"
1&
#2600
0"
0&
#2700
1"
1&
#2800
0"
0&
#2900
1"
1&
#3000
b10 +
1$
1(
0"
0&
#3100
b11 +
b10 ,
1"
1&
#3200
0"
0&
#3300
1*
1!
b0 +
b11 ,
1"
1&
#3400
0"
0&
#3500
0*
0!
b0 ,
0$
0(
1"
1&
#3600
0"
0&
#3700
1"
1&
#3800
0"
0&
#3900
1"
1&
#4000
b10 +
1#
1'
0"
0&
#4100
1*
1!
b0 +
b10 ,
1"
1&
#4200
0"
0&
#4300
0*
0!
b10 +
b0 ,
1"
1&
#4400
0"
0&
#4500
b10 ,
0#
0'
1"
1&
